event_dataframe
